<?xml version="1.0" encoding="utf-8" ?>
<localizationDictionary culture="zh-CN">
  <texts>
    <text name="HomePage" value="主页" />
    <text name="About" value="关于我们" />
    <text name="WellcomeMessage" value="欢迎使用 ABPBlog!" />
    <text name="Save">保存</text>
    <text name="Return">返回</text>
    <text name="Roles">角色列表</text>
    <text name="Users">用户列表</text>
    <text name="FormIsNotValidMessage" value="部分输入信息不符合要求，请检查并改正.." />
    <text name="TenantNameCanNotBeEmpty" value="租户名不能为空" />

    <text name="InvalidUserNameOrPassword" value="用户名或密码无效" />
    <text name="ThereIsNoTenantDefinedWithName{0}" value="租户 {0}不存在" />
    <text name="TenantIsNotActive" value="租户 {0} 未激活." />
    <text name="UserIsNotActiveAndCanNotLogin" value="用户 {0} 未激活，不能登录." />
    <text name="PleaseEnterLoginInformation" value="请输入登录信息" />
    <text name="TenancyName" value="租户名称" />
    <text name="UserNameOrEmail" value="用户名或邮箱地址" />
    <text name="Password" value="密码" />
    <text name="RememberMe" value="记住我" />
    <text name="LogIn" value="登录" />
    <text name="LoginFailed" value="登录失败!" />
    <text name="Title" value="标题" />
    <text name="Intro" value="简介" />
    <text name="Description" value="详情" />
    <text name="Content" value="内容" />
    <text name="SourceUrl" value="来源地址" />
    <text name="Memo" value="备注" />
    <text name="CLassName" value="分类名称" />
    <text name="Sort" value="序号" />
    <text name="CreateNewArticleClassify" value="创建文章分类" />
    <text name="Cancel" value="取消" />
    <text name="Edit" value="编辑" />
    <text name="Delete" value="删除" />


    <text name="ABPBlog_Pages_ArticlesManager" value="文章管理"></text>
    <text name="ABPBlog_Pages_Articles" value="文章列表"></text>
    <text name="ABPBlog_Pages_Articles_Create" value="添加文章"></text>
    <text name="ABPBlog_Pages_Articles_Edit" value="编辑文章"></text>
    <text name="ABPBlog_Pages_Articles_Delete" value="删除文章"></text>
    <text name="ABPBlog_Pages_ArticlesClassify" value="文章分类"></text>

  </texts>
</localizationDictionary>